IServAPI.py
iservapi-1.3.0.dist-info/licenses/LICENSE
iservapi-1.3.0.dist-info/METADATA
iservapi-1.3.0.dist-info/WHEEL
iservapi-1.3.0.dist-info/top_level.txt
iservapi-1.3.0.dist-info/RECORD
