Metadata-Version: 2.4
Name: IServAPI
Version: 1.3.0
Summary: Unofficial API for IServ
Home-page: https://github.com/Leo-Aqua/IServAPI
Author: Leo Aqua
Author-email: contact@leoaqua.de
Keywords: IServ,IServAPI,iserv api,iserv-api,API,Leo-Aqua
Classifier: Programming Language :: Python :: 3
Classifier: License :: OSI Approved :: MIT License
Classifier: Operating System :: OS Independent
Requires-Python: >=3.6
License-File: LICENSE
Requires-Dist: requests
Requires-Dist: beautifulsoup4
Requires-Dist: lxml
Requires-Dist: webdavclient
Requires-Dist: pandas
Requires-Dist: html5lib
Requires-Dist: dateutil
Requires-Dist: typing
Dynamic: author
Dynamic: author-email
Dynamic: classifier
Dynamic: description
Dynamic: description-content-type
Dynamic: home-page
Dynamic: keywords
Dynamic: license-file
Dynamic: requires-dist
Dynamic: requires-python
Dynamic: summary
